Pyomic/.DS_Store
Pyomic/__init__.py
Pyomic/__init__.pyc
Pyomic/.ipynb_checkpoints/__init__-checkpoint.py
Pyomic/__pycache__/__init__.cpython-38.pyc
Pyomic/bulk/.DS_Store
Pyomic/bulk/_DeGene.py
Pyomic/bulk/_Deseq2.py
Pyomic/bulk/_Enrichment.py
Pyomic/bulk/_Gene_module.py
Pyomic/bulk/__init__.py
Pyomic/bulk/_chm13.py
Pyomic/bulk/_df_apply.py
Pyomic/bulk/_dynamicTree.py
Pyomic/bulk/_network.py
Pyomic/bulk/_tcga.py
Pyomic/bulk/__pycache__/_DeGene.cpython-38.pyc
Pyomic/bulk/__pycache__/_Deseq2.cpython-38.pyc
Pyomic/bulk/__pycache__/_Enrichment.cpython-38.pyc
Pyomic/bulk/__pycache__/_Gene_module.cpython-38.pyc
Pyomic/bulk/__pycache__/__init__.cpython-38.pyc
Pyomic/bulk/__pycache__/_chm13.cpython-38.pyc
Pyomic/bulk/__pycache__/_df_apply.cpython-38.pyc
Pyomic/bulk/__pycache__/_dynamicTree.cpython-38.pyc
Pyomic/bulk/__pycache__/_network.cpython-38.pyc
Pyomic/bulk2single/__init__.py
Pyomic/bulk2single/_bulk2single.py
Pyomic/bulk2single/_map_utils copy.py
Pyomic/bulk2single/_map_utils.py
Pyomic/bulk2single/_map_utils1.py
Pyomic/bulk2single/_map_utils2.py
Pyomic/bulk2single/_single2spatial.py
Pyomic/bulk2single/_utils.py
Pyomic/bulk2single/_vae.py
Pyomic/mofapy2/__init__.py
Pyomic/mofapy2/config.py
Pyomic/mofapy2/version.py
Pyomic/mofapy2/__pycache__/__init__.cpython-38.pyc
Pyomic/mofapy2/__pycache__/config.cpython-38.pyc
Pyomic/mofapy2/__pycache__/version.cpython-38.pyc
Pyomic/mofapy2/build_model/__init__.py
Pyomic/mofapy2/build_model/build_model.py
Pyomic/mofapy2/build_model/init_model.py
Pyomic/mofapy2/build_model/save_model.py
Pyomic/mofapy2/build_model/train_model.py
Pyomic/mofapy2/build_model/utils.py
Pyomic/mofapy2/build_model/__pycache__/__init__.cpython-38.pyc
Pyomic/mofapy2/build_model/__pycache__/build_model.cpython-38.pyc
Pyomic/mofapy2/build_model/__pycache__/init_model.cpython-38.pyc
Pyomic/mofapy2/build_model/__pycache__/save_model.cpython-38.pyc
Pyomic/mofapy2/build_model/__pycache__/train_model.cpython-38.pyc
Pyomic-1.2.9.dist-info/LICENSE
Pyomic-1.2.9.dist-info/METADATA
Pyomic-1.2.9.dist-info/WHEEL
Pyomic-1.2.9.dist-info/top_level.txt
Pyomic-1.2.9.dist-info/RECORD
