Metadata-Version: 2.1
Name: Pyomic
Version: 1.2.9
Summary: A python framework library for omics analysis
Home-page: https://github.com/Starlitnightly/Pyomic
Author: ZehuaZeng
Author-email: Starlitnightly@163.com
License: GNU License
Platform: UNKNOWN
Requires-Python: >=3.8
License-File: LICENSE
Requires-Dist: pybind11
Requires-Dist: hnswlib
Requires-Dist: ERgene
Requires-Dist: numpy
Requires-Dist: scanpy
Requires-Dist: pandas (==1.5.3)
Requires-Dist: matplotlib
Requires-Dist: scikit-learn
Requires-Dist: scipy
Requires-Dist: networkx
Requires-Dist: multiprocess
Requires-Dist: seaborn
Requires-Dist: datetime
Requires-Dist: statsmodels
Requires-Dist: gseapy (==0.10.8)
Requires-Dist: ipywidgets
Requires-Dist: lifelines
Requires-Dist: ktplotspy
Requires-Dist: python-dotplot
Requires-Dist: boltons
Requires-Dist: ctxcore
Requires-Dist: termcolor
Requires-Dist: pygam (==0.8.0)
Requires-Dist: pillow
Requires-Dist: gdown
Requires-Dist: igraph
Requires-Dist: leidenalg
Requires-Dist: s-gd2
Requires-Dist: graphtools
Requires-Dist: datashader
Requires-Dist: phate
Requires-Dist: wget
